README.txt
setup.py
CAPTCHAmiddleware.egg-info/PKG-INFO
CAPTCHAmiddleware.egg-info/SOURCES.txt
CAPTCHAmiddleware.egg-info/dependency_links.txt
CAPTCHAmiddleware.egg-info/entry_points.txt
CAPTCHAmiddleware.egg-info/not-zip-safe
CAPTCHAmiddleware.egg-info/requires.txt
CAPTCHAmiddleware.egg-info/top_level.txt
captchamiddleware/__init__.py
captchamiddleware/example.py
captchamiddleware/middleware.py