Metadata-Version: 1.0
Name: CAPTCHAmiddleware
Version: 0.2
Summary: put CAPTCHAs on forms
Home-page: http://k0s.org/hg
Author: Jeff Hammel
Author-email: k0scist@gmail.com
License: GPL
Platform: UNKNOWN
